estream/__init__.py
estream/estream.py
estream/fading_cluster.py
estream/histogram.py
estream-0.0.3.dist-info/LICENSE
estream-0.0.3.dist-info/METADATA
estream-0.0.3.dist-info/WHEEL
estream-0.0.3.dist-info/top_level.txt
estream-0.0.3.dist-info/RECORD
