Metadata-Version: 2.1
Name: estream
Version: 0.0.3
Summary: An E-Stream implementation in Python
Home-page: https://github.com/mickeycj/estream
Author: Chanon Jenakom
Author-email: chanonjenakom@gmail.com
License: UNKNOWN
Keywords: machine learning,data mining,stream clustering,evolution-based
Platform: UNKNOWN
Classifier: Programming Language :: Python :: 3
Classifier: License :: OSI Approved :: GNU General Public License v3 (GPLv3)
Classifier: Operating System :: OS Independent
